androidd/__init__.py
androidd/cie1/activityCycle/MainActivity.kt
androidd/cie1/activityCycle/activity_main.xml
androidd/cie1/alert/MainActivity.kt
androidd/cie1/alert/activity_main.xml
androidd/cie1/autoCompleteText/MainActivity.kt
androidd/cie1/autoCompleteText/activity_main.xml
androidd/cie1/checkbox/MainActivity.kt
androidd/cie1/checkbox/activity_main.xml
androidd/cie1/customCheckbox/MainActivity.kt
androidd/cie1/customCheckbox/activity_main.xml
androidd/cie1/customCheckbox/custom_checkbox.xml
androidd/cie1/customRadio/MainActivity.kt
androidd/cie1/customRadio/activity_main.xml
androidd/cie1/customRadio/custom_checkbox.xml
androidd/cie1/customToast/MainActivity.kt
androidd/cie1/customToast/activity_main.xml
androidd/cie1/customToast/custom_toast.xml
androidd/cie1/datepicker/MainActivity.kt
androidd/cie1/datepicker/activity_main.xml
androidd/cie1/progressbar/MainActivity.kt
androidd/cie1/progressbar/activity_main.xml
androidd/cie1/ques1/MainActivity.kt
androidd/cie1/ques1/activity_main.xml
androidd/cie1/ques2/MainActivity.kt
androidd/cie1/ques2/activity_main.xml
androidd/cie1/ques3/AndroidManifest.xml
androidd/cie1/ques3/MainActivity.kt
androidd/cie1/ques3/activity_main.xml
androidd/cie1/radiobutton/MainActivity.kt
androidd/cie1/radiobutton/activity_main.xml
androidd/cie1/timePicker/MainActivity.kt
androidd/cie1/timePicker/activity_main.xml
androidd/cie1/toast/MainActivity.kt
androidd/cie1/toast/activity_main.xml
androidd/cie1/toggle/MainActivity.kt
androidd/cie1/toggle/activity_main.xml
androidd/madbmsj/package.json
androidd/madbmsj/IMPLICIT and EXPLICIT/Main Activity.kt
androidd/madbmsj/IMPLICIT and EXPLICIT/activity_main.xml
androidd/madbmsj/IMPLICIT and EXPLICIT/second.xml
androidd/madbmsj/IMPLICIT and EXPLICIT/secondactivity.kt
androidd/madbmsj/animation/MainActivity.kt
androidd/madbmsj/animation/activity_main.xml
androidd/madbmsj/animation/bounce.xml
androidd/madbmsj/animation/fad_in.xml
androidd/madbmsj/animation/fade_out.xml
androidd-0.0.3.dist-info/METADATA
androidd-0.0.3.dist-info/WHEEL
androidd-0.0.3.dist-info/top_level.txt
androidd-0.0.3.dist-info/RECORD
