Metadata-Version: 2.4
Name: androidd
Version: 0.0.3
Summary: A package containing the androidd folder.
Home-page: https://github.com/yourusername/androidd
Author: Your Name
Author-email: your.email@example.com
Keywords: androidd package
Classifier: Programming Language :: Python :: 3
Classifier: License :: OSI Approved :: MIT License
Classifier: Operating System :: OS Independent
Dynamic: author
Dynamic: author-email
Dynamic: classifier
Dynamic: description
Dynamic: description-content-type
Dynamic: home-page
Dynamic: keywords
Dynamic: summary
